hpipy/__init__.py
hpipy/period_table.py
hpipy/price_index.py
hpipy/price_model.py
hpipy/time_matrix.py
hpipy/trans_data.py
hpipy/version.txt
hpipy/datasets/__init__.py
hpipy/datasets/_base.py
hpipy/datasets/data/__init__.py
hpipy/datasets/data/ex_sales.csv
hpipy/datasets/data/seattle_sales.csv
hpipy/extensions/__init__.py
hpipy/extensions/forest/_base.py
hpipy/extensions/neural/__init__.py
hpipy/extensions/neural/_base.py
hpipy/extensions/neural/neural_avm/__init__.py
hpipy/extensions/neural/neural_avm/data_loader.py
hpipy/extensions/neural/neural_avm/data_pipeline.py
hpipy/extensions/neural/neural_avm/data_preprocessors.py
hpipy/extensions/neural/neural_avm/data_transformers.py
hpipy/extensions/neural/neural_avm/model_fnn.py
hpipy/extensions/neural/neural_avm/model_layers.py
hpipy/extensions/neural/neural_avm/utils/__init__.py
hpipy/extensions/neural/neural_avm/utils/data.py
hpipy/extensions/neural/neural_avm/utils/error.py
hpipy/extensions/neural/neural_avm/utils/model.py
hpipy/extensions/neural/neural_avm/utils/tests/__init__.py
hpipy/tests/__init__.py
hpipy/tests/conftest.py
hpipy/tests/test_hpipy.py
hpipy/tests/test_period_table.py
hpipy/tests/test_price_index.py
hpipy/tests/test_price_model.py
hpipy/tests/test_smooth_index.py
hpipy/tests/test_time_matrix.py
hpipy/tests/test_trans_data.py
hpipy/tests/extensions/test_forest.py
hpipy/tests/extensions/test_neural.py
hpipy/tests/utils/__init__.py
hpipy/tests/utils/test_metrics.py
hpipy/tests/utils/test_plotting.py
hpipy/tests/utils/test_stineman_interpolation.py
hpipy/utils/__init__.py
hpipy/utils/metrics.py
hpipy/utils/plotting.py
hpipy/utils/stineman_interpolation.py
hpipy-0.1.5.dist-info/licenses/LICENSE
hpipy-0.1.5.dist-info/METADATA
hpipy-0.1.5.dist-info/WHEEL
hpipy-0.1.5.dist-info/top_level.txt
hpipy-0.1.5.dist-info/RECORD
