Metadata-Version: 2.4
Name: hpipy
Version: 0.1.5
Summary: House Price Indices in Python.
Author-email: Reid Johnson <reid.johnson@gmail.com>
Maintainer-email: Reid Johnson <reid.johnson@gmail.com>
License:                                  Apache License
Project-URL: Homepage, https://github.com/reidjohnson/hpipy
Project-URL: Repository, https://github.com/reidjohnson/hpipy
Project-URL: Documentation, https://reidjohnson.github.io/hpipy
Project-URL: Bug Tracker, https://github.com/reidjohnson/hpipy/issues
Keywords: house prices,real estate,index,machine learning,regression
Classifier: Intended Audience :: Developers
Classifier: Intended Audience :: Science/Research
Classifier: License :: OSI Approved :: Apache Software License
Classifier: Operating System :: MacOS :: MacOS X
Classifier: Operating System :: Microsoft :: Windows
Classifier: Operating System :: POSIX
Classifier: Operating System :: Unix
Classifier: Programming Language :: Python
Classifier: Programming Language :: Python :: 3.10
Classifier: Programming Language :: Python :: 3.11
Classifier: Programming Language :: Python :: 3.12
Classifier: Topic :: Scientific/Engineering
Classifier: Topic :: Software Development
Requires-Python: >=3.10
License-File: LICENSE
Requires-Dist: altair~=5.5.0
Requires-Dist: captum~=0.8.0
Requires-Dist: h3~=4.2.1
Requires-Dist: numpy~=1.26.4; python_version < "3.13"
Requires-Dist: pandas~=2.2.3
Requires-Dist: quantile-forest~=1.4.0
Requires-Dist: scikit-learn~=1.6.1
Requires-Dist: scipy~=1.15.2
Requires-Dist: statsmodels~=0.14.4
Requires-Dist: torch~=2.6.0
Provides-Extra: dev
Requires-Dist: black>=25.1.0; extra == "dev"
Requires-Dist: flake8>=7.2.0; extra == "dev"
Requires-Dist: isort>=6.0.1; extra == "dev"
Requires-Dist: mypy>=1.15.0; extra == "dev"
Requires-Dist: pytest>=8.3.5; extra == "dev"
Requires-Dist: pytest-cov>=6.1.1; extra == "dev"
Requires-Dist: ruff>=0.11.5; extra == "dev"
Requires-Dist: types-python-dateutil>=2.9.0.post0; extra == "dev"
Dynamic: license-file
